pygentest/__init__.py
pygentest/gengraph.py
pygentest/genmisc.py
pygentest/gensequence.py
pygentest/genvalue.py
pygentest/wrapper.py
pygentest-0.0.8.dist-info/LICENSE
pygentest-0.0.8.dist-info/METADATA
pygentest-0.0.8.dist-info/WHEEL
pygentest-0.0.8.dist-info/top_level.txt
pygentest-0.0.8.dist-info/RECORD
