Metadata-Version: 2.1
Name: pygentest
Version: 0.0.8
Summary: Python test generators
Author-email: Thien-Phuoc Phung <phungthienphuoctthnnh@gmail.com>
Project-URL: Repository, https://github.com/phungthienphuoc/py-gentest
Project-URL: Issues, https://github.com/phungthienphuoc/py-gentest/issues
Project-URL: Documentation, https://github.com/phungthienphuoc/pygentest/blob/main/Documentation.md
Keywords: Python test,generator,testing,competitive programming,test generation,pygentest,test library
Classifier: Programming Language :: Python :: 3
Classifier: License :: OSI Approved :: Apache Software License
Classifier: Operating System :: OS Independent
Requires-Python: >=3.8
License-File: LICENSE
